setup.py
bglearn/__init__.py
bglearn/random_forest.py
bglearn.egg-info/PKG-INFO
bglearn.egg-info/SOURCES.txt
bglearn.egg-info/dependency_links.txt
bglearn.egg-info/requires.txt
bglearn.egg-info/top_level.txt