Metadata-Version: 2.1
Name: bglearn
Version: 0.1
Summary: A custom implementation of Random Forest Classifier
Home-page: 
Author: gautham-balraj
Author-email: gauthambalraj07@email.com
License: MIT
